<annotation>
	<folder>XML</folder>
	<filename>282.jpg</filename>
	<path>C:\Users\ADMIN\Desktop\Anh_da_xong\Anh_da_xong\282.jpg</path>
	<source>
		<database>Unknown</database>
	</source>
	<size>
		<width>1536</width>
		<height>2048</height>
		<depth>3</depth>
	</size>
	<segmented>0</segmented>
	<object>
		<name>gia_tien</name>
		<pose>Unspecified</pose>
		<truncated>0</truncated>
		<difficult>0</difficult>
		<bndbox>
			<xmin>1041</xmin>
			<ymin>841</ymin>
			<xmax>1269</xmax>
			<ymax>869</ymax>
		</bndbox>
	</object>
	<object>
		<name>ten_mon</name>
		<pose>Unspecified</pose>
		<truncated>0</truncated>
		<difficult>0</difficult>
		<bndbox>
			<xmin>505</xmin>
			<ymin>844</ymin>
			<xmax>949</xmax>
			<ymax>890</ymax>
		</bndbox>
	</object>
	<object>
		<name>gia_tien</name>
		<pose>Unspecified</pose>
		<truncated>0</truncated>
		<difficult>0</difficult>
		<bndbox>
			<xmin>1043</xmin>
			<ymin>923</ymin>
			<xmax>1232</xmax>
			<ymax>955</ymax>
		</bndbox>
	</object>
	<object>
		<name>ten_mon</name>
		<pose>Unspecified</pose>
		<truncated>0</truncated>
		<difficult>0</difficult>
		<bndbox>
			<xmin>548</xmin>
			<ymin>927</ymin>
			<xmax>920</xmax>
			<ymax>970</ymax>
		</bndbox>
	</object>
	<object>
		<name>ten_mon</name>
		<pose>Unspecified</pose>
		<truncated>0</truncated>
		<difficult>0</difficult>
		<bndbox>
			<xmin>497</xmin>
			<ymin>1220</ymin>
			<xmax>954</xmax>
			<ymax>1264</ymax>
		</bndbox>
	</object>
	<object>
		<name>gia_tien</name>
		<pose>Unspecified</pose>
		<truncated>0</truncated>
		<difficult>0</difficult>
		<bndbox>
			<xmin>1047</xmin>
			<ymin>1228</ymin>
			<xmax>1245</xmax>
			<ymax>1256</ymax>
		</bndbox>
	</object>
	<object>
		<name>ten_mon</name>
		<pose>Unspecified</pose>
		<truncated>0</truncated>
		<difficult>0</difficult>
		<bndbox>
			<xmin>529</xmin>
			<ymin>1303</ymin>
			<xmax>941</xmax>
			<ymax>1341</ymax>
		</bndbox>
	</object>
	<object>
		<name>gia_tien</name>
		<pose>Unspecified</pose>
		<truncated>0</truncated>
		<difficult>0</difficult>
		<bndbox>
			<xmin>1047</xmin>
			<ymin>1303</ymin>
			<xmax>1226</xmax>
			<ymax>1330</ymax>
		</bndbox>
	</object>
	<object>
		<name>ten_mon</name>
		<pose>Unspecified</pose>
		<truncated>0</truncated>
		<difficult>0</difficult>
		<bndbox>
			<xmin>573</xmin>
			<ymin>1626</ymin>
			<xmax>891</xmax>
			<ymax>1684</ymax>
		</bndbox>
	</object>
	<object>
		<name>gia_tien</name>
		<pose>Unspecified</pose>
		<truncated>0</truncated>
		<difficult>0</difficult>
		<bndbox>
			<xmin>1051</xmin>
			<ymin>1645</ymin>
			<xmax>1267</xmax>
			<ymax>1679</ymax>
		</bndbox>
	</object>
	<object>
		<name>ten_mon</name>
		<pose>Unspecified</pose>
		<truncated>0</truncated>
		<difficult>0</difficult>
		<bndbox>
			<xmin>614</xmin>
			<ymin>1701</ymin>
			<xmax>883</xmax>
			<ymax>1747</ymax>
		</bndbox>
	</object>
	<object>
		<name>gia_tien</name>
		<pose>Unspecified</pose>
		<truncated>0</truncated>
		<difficult>0</difficult>
		<bndbox>
			<xmin>1046</xmin>
			<ymin>1706</ymin>
			<xmax>1232</xmax>
			<ymax>1739</ymax>
		</bndbox>
	</object>
	<object>
		<name>menu</name>
		<pose>Unspecified</pose>
		<truncated>0</truncated>
		<difficult>0</difficult>
		<bndbox>
			<xmin>504</xmin>
			<ymin>842</ymin>
			<xmax>1268</xmax>
			<ymax>891</ymax>
		</bndbox>
	</object>
	<object>
		<name>menu</name>
		<pose>Unspecified</pose>
		<truncated>0</truncated>
		<difficult>0</difficult>
		<bndbox>
			<xmin>545</xmin>
			<ymin>925</ymin>
			<xmax>1235</xmax>
			<ymax>970</ymax>
		</bndbox>
	</object>
	<object>
		<name>menu</name>
		<pose>Unspecified</pose>
		<truncated>0</truncated>
		<difficult>0</difficult>
		<bndbox>
			<xmin>496</xmin>
			<ymin>1220</ymin>
			<xmax>1246</xmax>
			<ymax>1266</ymax>
		</bndbox>
	</object>
	<object>
		<name>menu</name>
		<pose>Unspecified</pose>
		<truncated>0</truncated>
		<difficult>0</difficult>
		<bndbox>
			<xmin>529</xmin>
			<ymin>1300</ymin>
			<xmax>1226</xmax>
			<ymax>1345</ymax>
		</bndbox>
	</object>
	<object>
		<name>menu</name>
		<pose>Unspecified</pose>
		<truncated>0</truncated>
		<difficult>0</difficult>
		<bndbox>
			<xmin>575</xmin>
			<ymin>1626</ymin>
			<xmax>1265</xmax>
			<ymax>1686</ymax>
		</bndbox>
	</object>
	<object>
		<name>menu</name>
		<pose>Unspecified</pose>
		<truncated>0</truncated>
		<difficult>0</difficult>
		<bndbox>
			<xmin>613</xmin>
			<ymin>1703</ymin>
			<xmax>1235</xmax>
			<ymax>1745</ymax>
		</bndbox>
	</object>
</annotation>
